odoo/addons/product_attribute_company_favorite/README.rst
odoo/addons/product_attribute_company_favorite/__init__.py
odoo/addons/product_attribute_company_favorite/__manifest__.py
odoo/addons/product_attribute_company_favorite/post_init_hook.py
odoo/addons/product_attribute_company_favorite/i18n/es.po
odoo/addons/product_attribute_company_favorite/i18n/it.po
odoo/addons/product_attribute_company_favorite/i18n/product_attribute_company_favorite.pot
odoo/addons/product_attribute_company_favorite/i18n/pt_BR.po
odoo/addons/product_attribute_company_favorite/models/__init__.py
odoo/addons/product_attribute_company_favorite/models/product_attribute.py
odoo/addons/product_attribute_company_favorite/models/product_attribute_is_favorite_mixin.py
odoo/addons/product_attribute_company_favorite/models/product_attribute_value.py
odoo/addons/product_attribute_company_favorite/models/product_template_attribute_line.py
odoo/addons/product_attribute_company_favorite/models/res_config_settings.py
odoo/addons/product_attribute_company_favorite/readme/CONFIGURE.md
odoo/addons/product_attribute_company_favorite/readme/CONTRIBUTORS.md
odoo/addons/product_attribute_company_favorite/readme/DESCRIPTION.md
odoo/addons/product_attribute_company_favorite/readme/USAGE.md
odoo/addons/product_attribute_company_favorite/static/description/icon.png
odoo/addons/product_attribute_company_favorite/static/description/index.html
odoo/addons/product_attribute_company_favorite/tests/__init__.py
odoo/addons/product_attribute_company_favorite/tests/test_product_attribute.py
odoo/addons/product_attribute_company_favorite/views/product_attribute_views.xml
odoo/addons/product_attribute_company_favorite/views/res_config_settings_views.xml
odoo_addon_product_attribute_company_favorite-17.0.1.0.0.2.dist-info/METADATA
odoo_addon_product_attribute_company_favorite-17.0.1.0.0.2.dist-info/WHEEL
odoo_addon_product_attribute_company_favorite-17.0.1.0.0.2.dist-info/top_level.txt
odoo_addon_product_attribute_company_favorite-17.0.1.0.0.2.dist-info/RECORD
